Metadata-Version: 2.1
Name: easyerrors
Version: 1.0.0
Summary: a simple module for testing out functions and catching its errors
Home-page: UNKNOWN
Author: Sjoerd Vermeulen
Author-email: sjoerd@marsenaar.com
License: UNKNOWN
Platform: UNKNOWN
Classifier: Programming Language :: Python :: 3
Classifier: License :: OSI Approved :: MIT License
Classifier: Operating System :: OS Independent
Requires-Python: >=3.6
